joshbasiccalculator/__init__.py
suhail-0.0.1.dist-info/LICENCE.txt
suhail-0.0.1.dist-info/METADATA
suhail-0.0.1.dist-info/WHEEL
suhail-0.0.1.dist-info/top_level.txt
suhail-0.0.1.dist-info/RECORD
