Metadata-Version: 2.1
Name: suhail
Version: 0.0.1
Summary: simple code for suhail
Home-page: UNKNOWN
Author: suhail
Author-email: hashemshaiban@gmail.com
License: MIT
Keywords: suhail
Platform: UNKNOWN
Classifier: Development Status :: 5 - Production/Stable
Classifier: Intended Audience :: Education
Classifier: Operating System :: Microsoft :: Windows :: Windows 10
Classifier: License :: OSI Approved :: MIT License
Classifier: Programming Language :: Python :: 3
License-File: LICENCE.txt
